jsm_user_services/__init__.py
jsm_user_services/apps.py
jsm_user_services/decorators/__init__.py
jsm_user_services/decorators/lgpd.py
jsm_user_services/decorators/lgpd_utils.py
jsm_user_services/drf/__init__.py
jsm_user_services/drf/authentications.py
jsm_user_services/drf/exceptions.py
jsm_user_services/drf/helpers.py
jsm_user_services/drf/models.py
jsm_user_services/drf/permissions/__init__.py
jsm_user_services/drf/permissions/base.py
jsm_user_services/drf/permissions/lo.py
jsm_user_services/drf/permissions/lv.py
jsm_user_services/drf_tools.py
jsm_user_services/enums.py
jsm_user_services/exception.py
jsm_user_services/middleware.py
jsm_user_services/services/__init__.py
jsm_user_services/services/everest.py
jsm_user_services/services/google.py
jsm_user_services/services/user.py
jsm_user_services/settings.py
jsm_user_services/support/__init__.py
jsm_user_services/support/auth_jwt.py
jsm_user_services/support/email_utils.py
jsm_user_services/support/http_utils.py
jsm_user_services/support/import_utils.py
jsm_user_services/support/local_threading_utils.py
jsm_user_services/support/logging_utils.py
jsm_user_services/support/request_id.py
jsm_user_services/support/settings_utils.py
jsm_user_services/support/string_utils.py
jsm_user_services/typings.py
jsm_user_services-2.5.1.dist-info/LICENSE
jsm_user_services-2.5.1.dist-info/METADATA
jsm_user_services-2.5.1.dist-info/WHEEL
jsm_user_services-2.5.1.dist-info/RECORD
