Metadata-Version: 2.1
Name: jsm-user-services
Version: 2.5.1
Summary: Middleware to intercept JWT auth token and more utils functions
License: MIT
Author: Juntos Somos Mais
Author-email: labs@juntossomosmais.com.br
Requires-Python: >=3.10,<4.0
Classifier: Development Status :: 5 - Production/Stable
Classifier: Environment :: Web Environment
Classifier: Framework :: Django :: 5.0
Classifier: Framework :: Django :: 5.1
Classifier: Framework :: Django :: 5.2
Classifier: Intended Audience :: Developers
Classifier: License :: OSI Approved :: MIT License
Classifier: Natural Language :: Portuguese (Brazilian)
Classifier: Operating System :: OS Independent
Classifier: Programming Language :: Python
Classifier: Programming Language :: Python :: 3
Classifier: Programming Language :: Python :: 3.10
Classifier: Programming Language :: Python :: 3.11
Classifier: Programming Language :: Python :: 3.12
Classifier: Programming Language :: Python :: 3.13
Provides-Extra: drf
Requires-Dist: PyJWT
Requires-Dist: pytest
Requires-Dist: requests
